{
  "main": {
    "id": "e92688fccef01641",
    "type": "split",
    "children": [
      {
        "id": "291e6fef508779de",
        "type": "tabs",
        "children": [
          {
            "id": "fd25ef31bc32fdb1",
            "type": "leaf",
            "state": {
              "type": "markdown",
              "state": {
                "file": "Testing.md",
                "mode": "source",
                "source": false
              }
            }
          },
          {
            "id": "75860b9b1c61dd3e",
            "type": "leaf",
            "state": {
              "type": "markdown",
              "state": {
                "file": "Again.md",
                "mode": "source",
                "source": false
              }
            }
          }
        ],
        "currentTab": 1
      }
    ],
    "direction": "vertical"
  },
  "left": {
    "id": "815893f81541e0c2",
    "type": "mobile-drawer",
    "children": [
      {
        "id": "82b684a182a3f2f2",
        "type": "leaf",
        "state": {
          "type": "file-explorer",
          "state": {
            "sortOrder": "alphabetical"
          }
        }
      },
      {
        "id": "aa9793fb1f26a600",
        "type": "leaf",
        "state": {
          "type": "search",
          "state": {
            "query": "",
            "matchingCase": false,
            "explainSearch": false,
            "collapseAll": false,
            "extraContext": false,
            "sortOrder": "alphabetical"
          }
        }
      },
      {
        "id": "227a26c89d2a337b",
        "type": "leaf",
        "state": {
          "type": "tag",
          "state": {
            "sortOrder": "frequency",
            "useHierarchy": true
          }
        }
      },
      {
        "id": "4a2eb23ff46ee956",
        "type": "leaf",
        "state": {
          "type": "bookmarks",
          "state": {}
        }
      }
    ],
    "currentTab": 0
  },
  "right": {
    "id": "a3fa061a8b0c65f2",
    "type": "mobile-drawer",
    "children": [
      {
        "id": "aa8280048c79ea52",
        "type": "leaf",
        "state": {
          "type": "backlink",
          "state": {
            "file": "Again.md",
            "collapseAll": false,
            "extraContext": false,
            "sortOrder": "alphabetical",
            "showSearch": false,
            "searchQuery": "",
            "backlinkCollapsed": false,
            "unlinkedCollapsed": true
          }
        }
      },
      {
        "id": "4f2b8f9dd79cedbd",
        "type": "leaf",
        "state": {
          "type": "outgoing-link",
          "state": {
            "file": "Again.md",
            "linksCollapsed": false,
            "unlinkedCollapsed": true
          }
        }
      },
      {
        "id": "b2c41d2987272140",
        "type": "leaf",
        "state": {
          "type": "outline",
          "state": {
            "file": "Again.md"
          }
        }
      }
    ],
    "currentTab": 0
  },
  "left-ribbon": {
    "hiddenItems": {
      "switcher:Open quick switcher": false,
      "graph:Open graph view": false,
      "canvas:Create new canvas": false,
      "daily-notes:Open today's daily note": false,
      "templates:Insert template": false,
      "command-palette:Open command palette": false
    }
  },
  "active": "75860b9b1c61dd3e",
  "lastOpenFiles": [
    "Testing.md",
    "Again.md",
    "/Testing.md",
    "README.md"
  ]
}